odoo/addons/shopinvader_wishlist/README.rst
odoo/addons/shopinvader_wishlist/__init__.py
odoo/addons/shopinvader_wishlist/__manifest__.py
odoo/addons/shopinvader_wishlist/demo/product_set.xml
odoo/addons/shopinvader_wishlist/i18n/shopinvader_wishlist.pot
odoo/addons/shopinvader_wishlist/models/__init__.py
odoo/addons/shopinvader_wishlist/models/product_set.py
odoo/addons/shopinvader_wishlist/readme/CONTRIBUTORS.rst
odoo/addons/shopinvader_wishlist/readme/CREDITS.rst
odoo/addons/shopinvader_wishlist/readme/DESCRIPTION.rst
odoo/addons/shopinvader_wishlist/services/__init__.py
odoo/addons/shopinvader_wishlist/services/wishlist.py
odoo/addons/shopinvader_wishlist/static/description/icon.png
odoo/addons/shopinvader_wishlist/static/description/index.html
odoo/addons/shopinvader_wishlist/tests/__init__.py
odoo/addons/shopinvader_wishlist/tests/test_product_set.py
odoo/addons/shopinvader_wishlist/tests/test_wishlist.py
odoo/addons/shopinvader_wishlist/views/product_set.xml
odoo/addons/shopinvader_wishlist/wizard/__init__.py
odoo/addons/shopinvader_wishlist/wizard/product_set_add.py
odoo/addons/shopinvader_wishlist/wizard/product_set_add.xml
odoo12_addon_shopinvader_wishlist-12.0.1.0.0.99.dev5.dist-info/METADATA
odoo12_addon_shopinvader_wishlist-12.0.1.0.0.99.dev5.dist-info/WHEEL
odoo12_addon_shopinvader_wishlist-12.0.1.0.0.99.dev5.dist-info/top_level.txt
odoo12_addon_shopinvader_wishlist-12.0.1.0.0.99.dev5.dist-info/RECORD
