Metadata-Version: 2.1
Name: odoo12-addon-shopinvader_wishlist
Version: 12.0.1.0.0.99.dev5
Summary: Handle shop wishlist
Home-page: https://github.com/shopinvader/odoo-shopinvader
Author: Camptocamp,Odoo Community Association (OCA)
Author-email: support@odoo-community.org
License: AGPL-3
Classifier: Programming Language :: Python
Classifier: Framework :: Odoo
Classifier: Framework :: Odoo :: 12.0
Classifier: License :: OSI Approved :: GNU Affero General Public License v3
Requires-Python: >=3.5
Requires-Dist: odoo12-addon-sale-wishlist
Requires-Dist: odoo12-addon-shopinvader
Requires-Dist: odoo<12.1dev,>=12.0a
